LICENSE.txt
MANIFEST.in
README.md
setup.py
practichem_device/__init__.py
practichem_device/device_manager.py
practichem_device/display.py
practichem_device/lighting.py
practichem_device/practichem_device.py
practichem_device/serial_handler.py
practichem_device/timer_thread.py
practichem_device/weak_callback.py
practichem_device.egg-info/PKG-INFO
practichem_device.egg-info/SOURCES.txt
practichem_device.egg-info/dependency_links.txt
practichem_device.egg-info/requires.txt
practichem_device.egg-info/top_level.txt
practichem_device.egg-info/zip-safe