Metadata-Version: 1.1
Name: practichem-device
Version: 2.0.0
Summary: Practichem device support package.
Home-page: https://www.practichem.com
Author: Practichem
Author-email: opensource@practichem.com
License: Apache License, Version 2.0
Platform: UNKNOWN
Classifier: License :: OSI Approved :: Apache Software License
Classifier: Programming Language :: Python :: 3
Classifier: Programming Language :: Python :: 3.2
Classifier: Programming Language :: Python :: 3.3
Classifier: Programming Language :: Python :: 3.4
